{
  "version": "1",
  "id": "1600d868742f45fba552b1055c3017e6",
  "experiment": {
    "base": {
      "analysis": {
        "variableFilters": [
          {
            "type": "text",
            "value": "*summary.*"
          },
          {
            "type": "text",
            "value": "*multiDisplay*"
          }
        ],
        "selectedType": "dynamic",
        "choices": [
          {
            "type": "dynamic",
            "parameters": {
              "final_time": 1000.0
            },
            "simulationOptions": {},
            "solverOptions": {},
            "compilerOptions": {},
            "runtimeOptions": {}
          },
          {
            "type": "steady state",
            "parameters": {},
            "simulationOptions": {},
            "solverOptions": {},
            "compilerOptions": {},
            "runtimeOptions": {}
          }
        ]
      },
      "modifiers": {
        "variables": []
      }
    }
  },
  "metadata": {
    "created": "2023-04-20T01:29:16.073Z",
    "lastModified": "2023-04-20T01:29:16.073Z",
    "name": "Experiment 1"
  }
}